semiring_torch/__init__.py
semiring_torch/defaults.py
semiring_torch/log_torch.py
semiring_torch/tensor_wrapper.py
semiring_torch/torch_semiring_einsum/__init__.py
semiring_torch/torch_semiring_einsum/equation.py
semiring_torch/torch_semiring_einsum/extend.py
semiring_torch/torch_semiring_einsum/function.py
semiring_torch/torch_semiring_einsum/log_backward.py
semiring_torch/torch_semiring_einsum/log_differentiable.py
semiring_torch/torch_semiring_einsum/log_forward.py
semiring_torch/torch_semiring_einsum/log_viterbi_forward.py
semiring_torch/torch_semiring_einsum/py.typed
semiring_torch/torch_semiring_einsum/real_backward.py
semiring_torch/torch_semiring_einsum/real_differentiable.py
semiring_torch/torch_semiring_einsum/real_forward.py
semiring_torch/torch_semiring_einsum/utils.py
semiring_torch-0.0.1.dist-info/LICENSE
semiring_torch-0.0.1.dist-info/METADATA
semiring_torch-0.0.1.dist-info/WHEEL
semiring_torch-0.0.1.dist-info/top_level.txt
semiring_torch-0.0.1.dist-info/RECORD
