Metadata-Version: 2.1
Name: semiring_torch
Version: 0.0.1
Summary: Semiring programming in PyTorch
Author-email: Jaron Maene <jaron.maene@gmail.com>
Project-URL: Homepage, https://github.com/jjcmoon/semiring_torch
Project-URL: Issues, https://github.com/jjcmoon/semiring_torch/issues
Classifier: Programming Language :: Python :: 3
Classifier: License :: OSI Approved :: MIT License
Classifier: Operating System :: OS Independent
Requires-Python: >=3.8
License-File: LICENSE
Requires-Dist: torch
Requires-Dist: autoray
